cutesdk/__init__.py
cutesdk/wxapp/__init__.py
cutesdk/wxapp/cache.py
cutesdk/wxapp/core.py
cutesdk/wxapp/token.py
cutesdk-0.1.4.dist-info/METADATA
cutesdk-0.1.4.dist-info/WHEEL
cutesdk-0.1.4.dist-info/top_level.txt
cutesdk-0.1.4.dist-info/RECORD
