Metadata-Version: 2.1
Name: cutesdk
Version: 0.1.4
Summary: sdks for open platforms
Home-page: https://cutesdk.com
Author: idoubi
Author-email: me@idoubi.cc
License: UNKNOWN
Platform: UNKNOWN
Requires-Dist: diskcache
Requires-Dist: requests
